pycomp/__init__.py
pycomp/fs/__init__.py
pycomp/fs/arquivos.py
pycomp/log/__init__.py
pycomp/log/log_config.py
pycomp/ml/__init__.py
pycomp/ml/trainer.py
pycomp/ml/trainer_test.py
pycomp/ml/transformers.py
pycomp/viz/__init__.py
pycomp/viz/formatador.py
pycomp/viz/insights.py
pycomp-0.3.3.dist-info/METADATA
pycomp-0.3.3.dist-info/WHEEL
pycomp-0.3.3.dist-info/top_level.txt
pycomp-0.3.3.dist-info/RECORD
